setup.py
emotion_data/__init__.py
emotion_data/behaviour.py
emotion_data/composite_emotions.py
emotion_data/deepmoji.py
emotion_data/emotions.py
emotion_data/feelings.py
emotion_data/lexicons.py
emotion_data/plutchik.py
emotion_data/reference_maps.py
emotion_data/tag.py
emotion_data.egg-info/PKG-INFO
emotion_data.egg-info/SOURCES.txt
emotion_data.egg-info/dependency_links.txt
emotion_data.egg-info/top_level.txt