Metadata-Version: 1.0
Name: emotion-data
Version: 0.6
Summary: structured data for working with human emotions
Home-page: https://github.com/JarbasAl/emotion_data
Author: jarbasAI
Author-email: jarbasai@mailfence.com
License: MIT
Platform: UNKNOWN
